projectilepy/__init__.py
projectilepy/model.py
projectilepy-0.2.1.dist-info/METADATA
projectilepy-0.2.1.dist-info/WHEEL
projectilepy-0.2.1.dist-info/licenses/LICENSE
projectilepy-0.2.1.dist-info/RECORD
