Metadata-Version: 2.1
Name: ProjectilePy
Version: 0.2.1
Summary: Simulate realistic projectile motion!
Project-URL: Homepage, https://github.com/ZCK12/ProjectilePy
Project-URL: Bug Tracker, https://github.com/ZCK12/ProjectilePy/issues
Author-email: Zachary Collins-Kenner <zachary.ck12@gmail.com>
License: MIT License
License-File: LICENSE
Keywords: ballistic,projectile,simulation
Classifier: Development Status :: 4 - Beta
Classifier: Programming Language :: Python :: 3
Requires-Python: >=3.7
Requires-Dist: numpy
